classifier_yan_zababurina6/__init__.py
classifier_yan_zababurina6/module.py
classifier_yan_zababurina6-0.1.dist-info/METADATA
classifier_yan_zababurina6-0.1.dist-info/WHEEL
classifier_yan_zababurina6-0.1.dist-info/top_level.txt
classifier_yan_zababurina6-0.1.dist-info/RECORD
